expay_sdk/__init__.py
expay_sdk/merchant_api.py
expay_sdk/requests/__init__.py
expay_sdk/requests/query.py
expay_sdk/requests/submit.py
expay_sdk/utility/__init__.py
expay_sdk/utility/config.py
tests/__init__.py
tests/test_config.py
tests/test_merchant_api.py
tests/test_query.py
tests/test_submit.py
expresspay_python_sdk-1.0.0.dist-info/METADATA
expresspay_python_sdk-1.0.0.dist-info/WHEEL
expresspay_python_sdk-1.0.0.dist-info/top_level.txt
expresspay_python_sdk-1.0.0.dist-info/RECORD
